penngrader/__init__.py
penngrader/backend.py
penngrader/grader.py
penngrader_client-0.5.13.dist-info/licenses/LICENSE
penngrader_client-0.5.13.dist-info/METADATA
penngrader_client-0.5.13.dist-info/WHEEL
penngrader_client-0.5.13.dist-info/top_level.txt
penngrader_client-0.5.13.dist-info/RECORD
