Metadata-Version: 2.4
Name: penngrader-client
Version: 0.5.13
Summary: In-line python grader client.
Home-page: https://github.com/upenn/PennGrader
Author: Leonardo Murri and Zachary Ives
Author-email: zives@cis.upenn.edu
Classifier: Programming Language :: Python :: 3
Classifier: License :: OSI Approved :: MIT License
Classifier: Operating System :: OS Independent
License-File: LICENSE
Requires-Dist: dill
Requires-Dist: pyyaml
Dynamic: author
Dynamic: author-email
Dynamic: classifier
Dynamic: description
Dynamic: description-content-type
Dynamic: home-page
Dynamic: license-file
Dynamic: requires-dist
Dynamic: summary
